[
  {
    "booking_hotel_id": "90809",
    "canonical_id": "33479e22-fe1e-4fd6-84e4-779a2e7f2c12",
    "name": "AC Hotel Aitana by Marriott",
    "wikidata": {
      "qid": "Q111409036",
      "label": "AC Hotel Aitana by Marriott",
      "inception": null,
      "capacity": null,
      "website": null,
      "coord": {
        "lon": -3.6897433,
        "lat": 40.45596
      },
      "distance_km": 0.000025382630512608092
    },
    "year_opened": null,
    "candidates": 2
  },
  {
    "booking_hotel_id": "243091",
    "canonical_id": "7f8a67b1-adfc-42b4-a7e3-26177b1d3e3e",
    "name": "AC Hotel Atocha by Marriott",
    "wikidata": {
      "qid": "Q111388623",
      "label": "AC Hotel Atocha by Marriott",
      "inception": null,
      "capacity": null,
      "website": null,
      "coord": {
        "lon": -3.69006,
        "lat": 40.404
      },
      "distance_km": 0.00045276782222521047
    },
    "year_opened": null,
    "candidates": 2
  },
  {
    "booking_hotel_id": "94071",
    "canonical_id": "3c21e3e2-d894-41ca-aa41-4d38890f6cb3",
    "name": "AC Hotel Madrid Feria by Marriott",
    "wikidata": {
      "qid": "Q111409050",
      "label": "AC Hotel Madrid Feria by Marriott",
      "inception": null,
      "capacity": null,
      "website": null,
      "coord": {
        "lon": -3.6344,
        "lat": 40.4748
      },
      "distance_km": 0.00008458503935779636
    },
    "year_opened": null,
    "candidates": 2
  },
  {
    "booking_hotel_id": "94455",
    "canonical_id": "651f9675-301c-43f7-820a-82e3f129b9f3",
    "name": "AC Hotel Recoletos by Marriott",
    "wikidata": {
      "qid": "Q111388878",
      "label": "AC Hotel Recoletos by Marriott",
      "inception": null,
      "capacity": null,
      "website": null,
      "coord": {
        "lon": -3.6893866,
        "lat": 40.421528
      },
      "distance_km": 0.00022495289144756493
    },
    "year_opened": null,
    "candidates": 2
  },
  {
    "booking_hotel_id": "4597290",
    "canonical_id": "af50ffcc-ad13-4bae-bdbc-20648467e6a3",
    "name": "Aloft by Marriott Madrid Gran Via",
    "wikidata": null,
    "year_opened": null,
    "candidates": 0
  },
  {
    "booking_hotel_id": "375331",
    "canonical_id": "225eabb9-4695-466d-b382-f1ffd841bb2d",
    "name": "Atocha Hotel Madrid, Tapestry Collection by Hilton",
    "wikidata": {
      "qid": "Q112011737",
      "label": "Atocha Hotel Madrid, Tapestry Collection by Hilton",
      "inception": null,
      "capacity": null,
      "website": null,
      "coord": {
        "lon": -3.69503,
        "lat": 40.41048
      },
      "distance_km": 0.0005121952624849773
    },
    "year_opened": null,
    "candidates": 2
  },
  {
    "booking_hotel_id": "2438985",
    "canonical_id": "0304bd68-d59c-4410-8417-8860763b4a94",
    "name": "Axel Hotel Madrid - Adults Only",
    "wikidata": {
      "qid": "Q111388638",
      "label": "Axel Hotel Madrid - Adults Only",
      "inception": null,
      "capacity": null,
      "website": null,
      "coord": {
        "lon": -3.70105,
        "lat": 40.41336
      },
      "distance_km": 0.00045276562116750366
    },
    "year_opened": null,
    "candidates": 2
  },
  {
    "booking_hotel_id": "92384",
    "canonical_id": "fa0b5629-4fb3-4945-94c7-d0adf075ef84",
    "name": "Barceló Emperatriz",
    "wikidata": {
      "qid": "Q111389175",
      "label": "Barceló Emperatriz",
      "inception": null,
      "capacity": null,
      "website": null,
      "coord": {
        "lon": -3.68805,
        "lat": 40.43663
      },
      "distance_km": 0.0004758991860469904
    },
    "year_opened": null,
    "candidates": 2
  },
  {
    "booking_hotel_id": "93360",
    "canonical_id": "461632b0-180e-4e5e-94ac-5f3455f5b372",
    "name": "Barceló Imagine",
    "wikidata": {
      "qid": "Q111389518",
      "label": "Barceló Imagine",
      "inception": null,
      "capacity": null,
      "website": null,
      "coord": {
        "lon": -3.68518,
        "lat": 40.47039
      },
      "distance_km": 0.00040490288001375567
    },
    "year_opened": null,
    "candidates": 2
  },
  {
    "booking_hotel_id": "1799501",
    "canonical_id": "291e4210-d4b8-4427-b0c5-8aecc2a4cbfa",
    "name": "Barceló Torre de Madrid",
    "wikidata": {
      "qid": "Q111389027",
      "label": "Barceló Torre de Madrid",
      "inception": null,
      "capacity": null,
      "website": null,
      "coord": {
        "lon": -3.71226,
        "lat": 40.42433
      },
      "distance_km": 0.0005811792522376187
    },
    "year_opened": null,
    "candidates": 2
  },
  {
    "booking_hotel_id": "8909003",
    "canonical_id": "2cc1d63d-ab80-4c88-9ba4-fd61021cd724",
    "name": "Bob W Madrid Atocha",
    "wikidata": null,
    "year_opened": null,
    "candidates": 0
  },
  {
    "booking_hotel_id": "7580435",
    "canonical_id": "33e350fc-d305-481c-b30f-aa2589825b71",
    "name": "Bob W Madrid Chueca",
    "wikidata": null,
    "year_opened": null,
    "candidates": 0
  },
  {
    "booking_hotel_id": "92250",
    "canonical_id": "2adc938d-afcb-4463-83d7-4693bb9c35f7",
    "name": "Canopy by Hilton Madrid Castellana",
    "wikidata": {
      "qid": "Q112011952",
      "label": "Canopy by Hilton Madrid Castellana",
      "inception": null,
      "capacity": null,
      "website": "https://www.hilton.com/en/hotels/madespy-canopy-madrid-castellana/",
      "coord": {
        "lon": -3.6935368,
        "lat": 40.451355
      },
      "distance_km": 0.01753167043035915
    },
    "year_opened": null,
    "candidates": 2
  },
  {
    "booking_hotel_id": "91651",
    "canonical_id": "ee3c988b-3efe-4ac0-bb5d-0e8b98ef8579",
    "name": "Casa de las Artes member of Meliá Collection",
    "wikidata": null,
    "year_opened": null,
    "candidates": 0
  },
  {
    "booking_hotel_id": "266093",
    "canonical_id": "d2af52ca-523b-4892-b5aa-2a97b0152067",
    "name": "Catalonia Atocha",
    "wikidata": {
      "qid": "Q111388635",
      "label": "Catalonia Atocha",
      "inception": null,
      "capacity": null,
      "website": null,
      "coord": {
        "lon": -3.69793,
        "lat": 40.41184
      },
      "distance_km": 0.0004759213822985253
    },
    "year_opened": null,
    "candidates": 2
  },
  {
    "booking_hotel_id": "91604",
    "canonical_id": "c285b171-6cd9-4686-847f-ea0219c93314",
    "name": "Catalonia Goya",
    "wikidata": {
      "qid": "Q111389022",
      "label": "Catalonia Goya",
      "inception": null,
      "capacity": null,
      "website": null,
      "coord": {
        "lon": -3.68209,
        "lat": 40.42514
      },
      "distance_km": 0.0003563813712066956
    },
    "year_opened": null,
    "candidates": 2
  },
  {
    "booking_hotel_id": "90576",
    "canonical_id": "68dfb451-7e6d-4460-9a39-4e9b6cf0a5dd",
    "name": "Catalonia Gran Vía Madrid",
    "wikidata": null,
    "year_opened": null,
    "candidates": 0
  },
  {
    "booking_hotel_id": "92345",
    "canonical_id": "b6f3621a-579a-415a-a1fc-7d6a846cf8ac",
    "name": "Catalonia Las Cortes",
    "wikidata": {
      "qid": "Q111388645",
      "label": "Catalonia Las Cortes Madrid",
      "inception": null,
      "capacity": null,
      "website": null,
      "coord": {
        "lon": -3.69914,
        "lat": 40.41469
      },
      "distance_km": 0.0003740969814107281
    },
    "year_opened": null,
    "candidates": 2
  },
  {
    "booking_hotel_id": "13414681",
    "canonical_id": "fc9d8ed0-9c80-4e19-ab57-dfb662ed8d74",
    "name": "Catalonia Plaza España Hotel & Spa",
    "wikidata": null,
    "year_opened": null,
    "candidates": 0
  },
  {
    "booking_hotel_id": "266096",
    "canonical_id": "23d20597-0a88-46c3-928c-480de2d74ea1",
    "name": "Catalonia Plaza Mayor",
    "wikidata": {
      "qid": "Q111388636",
      "label": "Catalonia Plaza Mayor",
      "inception": null,
      "capacity": null,
      "website": null,
      "coord": {
        "lon": -3.70078,
        "lat": 40.41315
      },
      "distance_km": 0.00041927162155801256
    },
    "year_opened": null,
    "candidates": 4
  },
  {
    "booking_hotel_id": "90575",
    "canonical_id": "d9b782dc-e7e2-430b-afb4-aec308495da6",
    "name": "Catalonia Puerta del Sol",
    "wikidata": {
      "qid": "Q111388642",
      "label": "Catalonia Puerta del Sol Madrid",
      "inception": null,
      "capacity": null,
      "website": null,
      "coord": {
        "lon": -3.70274,
        "lat": 40.41389
      },
      "distance_km": 0.00034416044655836097
    },
    "year_opened": null,
    "candidates": 2
  },
  {
    "booking_hotel_id": "2376771",
    "canonical_id": "db052e04-ba29-41c4-a00f-96a93a740a1c",
    "name": "Círculo Gran Vía, Autograph Collection",
    "wikidata": {
      "qid": "Q111871838",
      "label": "Círculo Gran Vía, Autograph Collection (Adults Only)",
      "inception": null,
      "capacity": null,
      "website": null,
      "coord": {
        "lon": -3.70081,
        "lat": 40.42012
      },
      "distance_km": 0.00044477970703544903
    },
    "year_opened": null,
    "candidates": 2
  },
  {
    "booking_hotel_id": "10199915",
    "canonical_id": "8a99c6fe-18eb-4834-83a1-704c71cd7909",
    "name": "Crowne Plaza Madrid - Centre Retiro by IHG",
    "wikidata": null,
    "year_opened": null,
    "candidates": 0
  },
  {
    "booking_hotel_id": "1909037",
    "canonical_id": "550c9ba0-48de-471f-975a-b3b030ffa4e2",
    "name": "DoubleTree by Hilton Madrid-Prado",
    "wikidata": {
      "qid": "Q72172868",
      "label": "DoubleTree by Hilton Madrid - Prado",
      "inception": "1992-01-01T00:00:00Z",
      "capacity": null,
      "website": "https://doubletree3.hilton.com/en/hotels/spain/doubletree-by-hilton-madrid-prado-MADPRDI/index.html",
      "coord": {
        "lon": -3.69679,
        "lat": 40.4151
      },
      "distance_km": 0.0005121866234007381
    },
    "year_opened": 1992,
    "candidates": 8
  },
  {
    "booking_hotel_id": "13016408",
    "canonical_id": "518702d0-643d-4cdc-933b-9e1039d61a8f",
    "name": "El Autor Hotel, Madrid, Autograph Collection",
    "wikidata": null,
    "year_opened": null,
    "candidates": 0
  },
  {
    "booking_hotel_id": "92587",
    "canonical_id": "2888ba78-1e18-4d1c-89bb-fc8da6817e43",
    "name": "Eurostars Casa de la Lírica",
    "wikidata": {
      "qid": "Q111662118",
      "label": "Eurostars Casa de la Lírica",
      "inception": null,
      "capacity": null,
      "website": null,
      "coord": {
        "lon": -3.70139,
        "lat": 40.41832
      },
      "distance_km": 0.00037409284694218893
    },
    "year_opened": null,
    "candidates": 2
  },
  {
    "booking_hotel_id": "1187995",
    "canonical_id": "f95382b8-0729-46a9-9e8c-b15093542909",
    "name": "Eurostars Central",
    "wikidata": {
      "qid": "Q111389034",
      "label": "Eurostars Central",
      "inception": null,
      "capacity": null,
      "website": null,
      "coord": {
        "lon": -3.69853,
        "lat": 40.42707
      },
      "distance_km": 0.0005121642092442349
    },
    "year_opened": null,
    "candidates": 4
  },
  {
    "booking_hotel_id": "90302",
    "canonical_id": "525d3e1d-d6c8-4d64-9279-9d92d6985fff",
    "name": "Eurostars Madrid Gran Vía",
    "wikidata": {
      "qid": "Q111871932",
      "label": "Eurostars Madrid Gran Vía",
      "inception": null,
      "capacity": null,
      "website": null,
      "coord": {
        "lon": -3.70986,
        "lat": 40.42114
      },
      "distance_km": 0.0002379565294034839
    },
    "year_opened": null,
    "candidates": 2
  },
  {
    "booking_hotel_id": "12196",
    "canonical_id": "8f2edc75-4e8a-4056-a823-06c013c0e5f7",
    "name": "Eurostars Madrid Tower",
    "wikidata": {
      "qid": "Q111389522",
      "label": "Eurostars Madrid Tower",
      "inception": null,
      "capacity": null,
      "website": null,
      "coord": {
        "lon": -3.68736,
        "lat": 40.47816
      },
      "distance_km": 0.00023793099673113921
    },
    "year_opened": null,
    "candidates": 2
  },
  {
    "booking_hotel_id": "94069",
    "canonical_id": "f8e537e1-999e-42f3-aa38-cac6748edfa0",
    "name": "Eurostars Monte Real",
    "wikidata": {
      "qid": "Q111872205",
      "label": "Eurostars Monte Real",
      "inception": null,
      "capacity": null,
      "website": null,
      "coord": {
        "lon": -3.74296,
        "lat": 40.47504
      },
      "distance_km": 0.00013971001929716757
    },
    "year_opened": null,
    "candidates": 2
  },
  {
    "booking_hotel_id": "482850",
    "canonical_id": "79257f39-d5e0-4ab1-b6ad-331744e54639",
    "name": "Eurostars Plaza Mayor",
    "wikidata": {
      "qid": "Q111388639",
      "label": "Eurostars Plaza Mayor",
      "inception": null,
      "capacity": null,
      "website": null,
      "coord": {
        "lon": -3.7039175,
        "lat": 40.413036
      },
      "distance_km": 0.00011898007859953376
    },
    "year_opened": null,
    "candidates": 2
  },
  {
    "booking_hotel_id": "90767",
    "canonical_id": "20dafe47-678b-4720-8f17-0cd3386eca35",
    "name": "Eurostars Suites Mirasierra",
    "wikidata": {
      "qid": "Q111389525",
      "label": "Eurostars Suites Mirasierra",
      "inception": null,
      "capacity": null,
      "website": null,
      "coord": {
        "lon": -3.70355,
        "lat": 40.48664
      },
      "distance_km": 0.00008457012215850542
    },
    "year_opened": null,
    "candidates": 2
  },
  {
    "booking_hotel_id": "5853235",
    "canonical_id": "fa20d9a6-94fa-4227-95f8-74f528e955e3",
    "name": "Four Seasons Hotel Madrid",
    "wikidata": {
      "qid": "Q111516030",
      "label": "Four Seasons Hotel Madrid",
      "inception": null,
      "capacity": null,
      "website": null,
      "coord": {
        "lon": -3.700203,
        "lat": 40.416855
      },
      "distance_km": 0.05973884730889744
    },
    "year_opened": null,
    "candidates": 4
  },
  {
    "booking_hotel_id": "7020213",
    "canonical_id": "cd0dea49-1dc8-4637-89bb-c019b315202d",
    "name": "Hard Rock Hotel Madrid",
    "wikidata": null,
    "year_opened": null,
    "candidates": 0
  },
  {
    "booking_hotel_id": "12793",
    "canonical_id": "370c1972-aa94-4841-b90b-10b773b0df18",
    "name": "Hilton Madrid Airport",
    "wikidata": {
      "qid": "Q111389327",
      "label": "Hilton Madrid Airport",
      "inception": null,
      "capacity": null,
      "website": null,
      "coord": {
        "lon": -3.5858345,
        "lat": 40.45254
      },
      "distance_km": 0.00004230653746040007
    },
    "year_opened": null,
    "candidates": 2
  },
  {
    "booking_hotel_id": "276985",
    "canonical_id": "798b830c-9f0b-4ec1-b31b-df027696fdc2",
    "name": "Hotel Crowne Plaza Madrid Airport",
    "wikidata": null,
    "year_opened": null,
    "candidates": 0
  },
  {
    "booking_hotel_id": "91584",
    "canonical_id": "89640384-6f55-4e72-84fe-3e6f06ad3973",
    "name": "Hotel Fénix Gran Meliá",
    "wikidata": {
      "qid": "Q26702361",
      "label": "Hotel Fénix, Madrid",
      "inception": null,
      "capacity": null,
      "website": null,
      "coord": {
        "lon": -3.689627,
        "lat": 40.426337
      },
      "distance_km": 0.031994320673823524
    },
    "year_opened": null,
    "candidates": 4
  },
  {
    "booking_hotel_id": "743453",
    "canonical_id": "af8e6ebf-2b47-4b7d-8c9d-b438e7acb676",
    "name": "Hotel Indigo Madrid Gran Vía by IHG",
    "wikidata": null,
    "year_opened": null,
    "candidates": 0
  },
  {
    "booking_hotel_id": "91639",
    "canonical_id": "dea209e1-4a94-422e-87fe-e80a324e876e",
    "name": "Hotel Madrid Plaza España Affiliated by Meliá",
    "wikidata": null,
    "year_opened": null,
    "candidates": 0
  },
  {
    "booking_hotel_id": "8985080",
    "canonical_id": "b739dd6f-1979-4aa3-8a87-f4aafe283a2b",
    "name": "Hotel Montera Madrid Curio Collection By Hilton",
    "wikidata": null,
    "year_opened": null,
    "candidates": 0
  },
  {
    "booking_hotel_id": "91303",
    "canonical_id": "9717c946-1996-4ed6-9e9a-a24d0fa1c0bb",
    "name": "Hotel Palacio del Retiro Autograph Collection",
    "wikidata": null,
    "year_opened": null,
    "candidates": 0
  },
  {
    "booking_hotel_id": "2765660",
    "canonical_id": "f95cfc46-fec5-4279-901c-7cd076d38ecc",
    "name": "Hyatt Centric Gran Via Madrid",
    "wikidata": {
      "qid": "Q111388877",
      "label": "Hyatt Centric Gran Via Madrid",
      "inception": null,
      "capacity": null,
      "website": "https://www.hyatt.com/hyatt-centric/madct-hyatt-centric-gran-via-madrid",
      "coord": {
        "lon": -3.70371,
        "lat": 40.42005
      },
      "distance_km": 0.0002772381019724621
    },
    "year_opened": null,
    "candidates": 2
  },
  {
    "booking_hotel_id": "91812",
    "canonical_id": "d3868189-c30d-4515-a51f-7e7a881b17e5",
    "name": "Hyatt Regency Hesperia Madrid",
    "wikidata": {
      "qid": "Q111389314",
      "label": "Hyatt Regency Hesperia Madrid",
      "inception": null,
      "capacity": null,
      "website": "https://www.hyatt.com/hyatt-regency/en-US/madrm-hyatt-regency-hesperia-madrid",
      "coord": {
        "lon": -3.69162,
        "lat": 40.43884
      },
      "distance_km": 0.00013973762326021942
    },
    "year_opened": null,
    "candidates": 2
  },
  {
    "booking_hotel_id": "7771044",
    "canonical_id": "05ceb6e8-d76e-49e2-ae5b-f566179f8eda",
    "name": "Hyatt Regency Madrid Residences",
    "wikidata": {
      "qid": "Q136468059",
      "label": "Hyatt Regency Madrid Residences",
      "inception": null,
      "capacity": null,
      "website": "https://www.hyatt.com/hyatt-regency/en-US/madra-hyatt-regency-madrid-residences",
      "coord": {
        "lon": -3.689268,
        "lat": 40.43706
      },
      "distance_km": 0.018461359452924545
    },
    "year_opened": null,
    "candidates": 2
  },
  {
    "booking_hotel_id": "4904720",
    "canonical_id": "2ea36513-b4b8-4f9b-92f6-0635594e7461",
    "name": "Ibis Styles Madrid City Las Ventas",
    "wikidata": {
      "qid": "Q112011950",
      "label": "Ibis Styles Madrid City Las Ventas",
      "inception": null,
      "capacity": null,
      "website": null,
      "coord": {
        "lon": -3.657524,
        "lat": 40.441433
      },
      "distance_km": 0
    },
    "year_opened": null,
    "candidates": 2
  },
  {
    "booking_hotel_id": "92767",
    "canonical_id": "c6dc6789-e03d-4410-9af6-7c6b0da73d1e",
    "name": "Ilunion Alcalá Norte",
    "wikidata": null,
    "year_opened": null,
    "candidates": 0
  },
  {
    "booking_hotel_id": "17328",
    "canonical_id": "c43c95c0-c2a2-419d-848a-e38fd9fda05c",
    "name": "Ilunion Atrium",
    "wikidata": {
      "qid": "Q111389318",
      "label": "Hotel ILUNION Atrium",
      "inception": null,
      "capacity": null,
      "website": "https://www.ilunionhotels.com/hoteles/ilunion-atrium",
      "coord": {
        "lon": -3.65469,
        "lat": 40.44787
      },
      "distance_km": 0.0005623772408776821
    },
    "year_opened": null,
    "candidates": 2
  },
  {
    "booking_hotel_id": "90364",
    "canonical_id": "b0c3d92d-067a-4f32-9d14-9f7d796b5088",
    "name": "Ilunion Pio XII",
    "wikidata": null,
    "year_opened": null,
    "candidates": 0
  },
  {
    "booking_hotel_id": "90361",
    "canonical_id": "d6f2ab36-8c6b-4950-8ad2-ec5898ad28d9",
    "name": "Ilunion Suites Madrid",
    "wikidata": null,
    "year_opened": null,
    "candidates": 0
  },
  {
    "booking_hotel_id": "91620",
    "canonical_id": "67b98fd6-3447-46e0-8364-ce8c8c85cc6e",
    "name": "INNSiDE by Meliá Madrid Gran Vía",
    "wikidata": null,
    "year_opened": null,
    "candidates": 0
  },
  {
    "booking_hotel_id": "11705130",
    "canonical_id": "4520d3f5-f18f-4f6c-af4c-97e0bc6831f3",
    "name": "INNSiDE by Meliá Madrid Valdebebas",
    "wikidata": null,
    "year_opened": null,
    "candidates": 0
  },
  {
    "booking_hotel_id": "188656",
    "canonical_id": "1a24452a-fc44-45a8-874e-7d4c41ee55cd",
    "name": "InterContinental Madrid by IHG",
    "wikidata": null,
    "year_opened": null,
    "candidates": 0
  },
  {
    "booking_hotel_id": "91764",
    "canonical_id": "6f7bc75e-e348-4625-bc2c-69cf2df4e1c8",
    "name": "Madrid Alameda Aeropuerto by Meliá",
    "wikidata": null,
    "year_opened": null,
    "candidates": 0
  },
  {
    "booking_hotel_id": "90738",
    "canonical_id": "eafb935d-a6eb-44d3-b2b8-11feff59a23e",
    "name": "Madrid Marriott Auditorium Hotel & Conference Center",
    "wikidata": {
      "qid": "Q111389510",
      "label": "Madrid Marriott Auditorium Hotel & Conference Center",
      "inception": null,
      "capacity": null,
      "website": "https://www.marriott.com/en-us/hotels/madad-madrid-marriott-auditorium-hotel-and-conference-center/overview/?scid=cf432f1f-54d2-411a-89ce-225188630324",
      "coord": {
        "lon": -3.55868,
        "lat": 40.44911
      },
      "distance_km": 0.0003374880366866441
    },
    "year_opened": null,
    "candidates": 2
  },
  {
    "booking_hotel_id": "90764",
    "canonical_id": "737f2c2f-0ac1-4e71-9761-a45ce20b7d74",
    "name": "Madrid Marriott Hotel Princesa Plaza",
    "wikidata": null,
    "year_opened": null,
    "candidates": 0
  },
  {
    "booking_hotel_id": "12136",
    "canonical_id": "dafc4073-ab60-43ec-91a0-ac1d7311232e",
    "name": "Mandarin Oriental Ritz Madrid",
    "wikidata": null,
    "year_opened": null,
    "candidates": 0
  },
  {
    "booking_hotel_id": "90024",
    "canonical_id": "f779cfbc-5c5d-43f8-ab6e-d299bbc627a0",
    "name": "Meliá Avenida América",
    "wikidata": null,
    "year_opened": null,
    "candidates": 0
  },
  {
    "booking_hotel_id": "91471",
    "canonical_id": "6a8cb14d-43b0-42f0-b183-b0e4399d3052",
    "name": "Meliá Castilla",
    "wikidata": {
      "qid": "Q111389511",
      "label": "Melia Castilla",
      "inception": null,
      "capacity": null,
      "website": null,
      "coord": {
        "lon": -3.6919723,
        "lat": 40.461426
      },
      "distance_km": 0.00011405474536121409
    },
    "year_opened": null,
    "candidates": 2
  },
  {
    "booking_hotel_id": "91436",
    "canonical_id": "bd9fd2f0-2b0e-4711-aa0f-6b8028c72b65",
    "name": "Meliá Madrid Barajas",
    "wikidata": null,
    "year_opened": null,
    "candidates": 0
  },
  {
    "booking_hotel_id": "91437",
    "canonical_id": "9dbba777-d08f-4c63-99b6-c95156107e93",
    "name": "Meliá Madrid Serrano",
    "wikidata": {
      "qid": "Q111872034",
      "label": "Melia Madrid Serrano",
      "inception": null,
      "capacity": null,
      "website": null,
      "coord": {
        "lon": -3.68546,
        "lat": 40.43538
      },
      "distance_km": 0.0005589610372706064
    },
    "year_opened": null,
    "candidates": 2
  },
  {
    "booking_hotel_id": "90286",
    "canonical_id": "c8cf9188-ad2b-40c5-a1ae-50727b748f3c",
    "name": "Mercure Madrid Centro",
    "wikidata": {
      "qid": "Q111388637",
      "label": "Mercure Madrid Centro",
      "inception": null,
      "capacity": null,
      "website": null,
      "coord": {
        "lon": -3.69445,
        "lat": 40.41394
      },
      "distance_km": 0.0002772592330725553
    },
    "year_opened": null,
    "candidates": 2
  },
  {
    "booking_hotel_id": "93625",
    "canonical_id": "eb20a0cc-5759-417b-b14d-bf571e8be58b",
    "name": "Motel One Madrid-Plaza de España",
    "wikidata": null,
    "year_opened": null,
    "candidates": 0
  },
  {
    "booking_hotel_id": "90661",
    "canonical_id": "ec71ab4c-cba0-4e13-941d-e77f9d8d0fe0",
    "name": "NH Collection Madrid Abascal",
    "wikidata": {
      "qid": "Q111389311",
      "label": "NH Collection Madrid Abascal",
      "inception": null,
      "capacity": null,
      "website": null,
      "coord": {
        "lon": -3.69515,
        "lat": 40.43837
      },
      "distance_km": 0.0004758976287364182
    },
    "year_opened": null,
    "candidates": 2
  },
  {
    "booking_hotel_id": "90659",
    "canonical_id": "7e5d4cb7-9d21-4a9b-89b4-bdb7e045b32c",
    "name": "NH Collection Madrid Eurobuilding",
    "wikidata": {
      "qid": "Q111389328",
      "label": "NH Collection Madrid Eurobuilding",
      "inception": null,
      "capacity": null,
      "website": null,
      "coord": {
        "lon": -3.68584,
        "lat": 40.45829
      },
      "distance_km": 0.00041916838257756396
    },
    "year_opened": null,
    "candidates": 2
  },
  {
    "booking_hotel_id": "2775742",
    "canonical_id": "23605208-bdeb-4a6f-b92c-a3c7b1ab94a3",
    "name": "NH Collection Madrid Gran Vía",
    "wikidata": {
      "qid": "Q111662127",
      "label": "NH Collection Madrid Gran Vía",
      "inception": null,
      "capacity": null,
      "website": null,
      "coord": {
        "lon": -3.70112,
        "lat": 40.41988
      },
      "distance_km": 0.0003441585925877872
    },
    "year_opened": null,
    "candidates": 2
  },
  {
    "booking_hotel_id": "257117",
    "canonical_id": "fb8b5471-338f-4165-8cf8-2766b30369e1",
    "name": "NH Collection Madrid Palacio de Tepa",
    "wikidata": {
      "qid": "Q16615310",
      "label": "NH Collection Madrid Palacio de Tepa",
      "inception": null,
      "capacity": null,
      "website": null,
      "coord": {
        "lon": -3.70182222,
        "lat": 40.41363611
      },
      "distance_km": 0.05601608284882763
    },
    "year_opened": null,
    "candidates": 4
  },
  {
    "booking_hotel_id": "12857",
    "canonical_id": "fe0dba16-de54-4313-83ef-3422298c8bf4",
    "name": "NH Collection Madrid Paseo del Prado",
    "wikidata": null,
    "year_opened": null,
    "candidates": 0
  },
  {
    "booking_hotel_id": "628125",
    "canonical_id": "bbcd84a5-63c1-4cf2-9192-38cc223a0494",
    "name": "NH Collection Madrid Suecia",
    "wikidata": {
      "qid": "Q111388750",
      "label": "NH Collection Madrid Suecia",
      "inception": null,
      "capacity": null,
      "website": null,
      "coord": {
        "lon": -3.696159124,
        "lat": 40.417891731
      },
      "distance_km": 0.000031700000150848977
    },
    "year_opened": null,
    "candidates": 2
  },
  {
    "booking_hotel_id": "90676",
    "canonical_id": "73617f4f-3a93-47d4-bcf4-560db5ab7fd8",
    "name": "NH Madrid Lagasca",
    "wikidata": {
      "qid": "Q111389029",
      "label": "NH Madrid Lagasca",
      "inception": null,
      "capacity": null,
      "website": null,
      "coord": {
        "lon": -3.68504,
        "lat": 40.42752
      },
      "distance_km": 0.0006139597404248024
    },
    "year_opened": null,
    "candidates": 2
  },
  {
    "booking_hotel_id": "90358",
    "canonical_id": "5424a3d2-89e6-40c3-8a19-5aa4938138c0",
    "name": "NH Madrid Nacional",
    "wikidata": {
      "qid": "Q111388630",
      "label": "NH Madrid Nacional",
      "inception": null,
      "capacity": null,
      "website": null,
      "coord": {
        "lon": -3.69264,
        "lat": 40.409912
      },
      "distance_km": 0
    },
    "year_opened": null,
    "candidates": 2
  },
  {
    "booking_hotel_id": "276495",
    "canonical_id": "a3c92494-43b8-4a88-bb0a-94a461e24617",
    "name": "NH Madrid Ribera del Manzanares",
    "wikidata": {
      "qid": "Q111388632",
      "label": "NH Madrid Ribera del Manzanares",
      "inception": null,
      "capacity": null,
      "website": null,
      "coord": {
        "lon": -3.7218251,
        "lat": 40.40616
      },
      "distance_km": 0.000008467144783467903
    },
    "year_opened": null,
    "candidates": 2
  },
  {
    "booking_hotel_id": "93548",
    "canonical_id": "deb5f877-8b19-4122-9a77-06756a20ebf0",
    "name": "Novotel Campo De Las Naciones",
    "wikidata": null,
    "year_opened": null,
    "candidates": 0
  },
  {
    "booking_hotel_id": "90218",
    "canonical_id": "c74d49ee-a057-41e6-b9bf-462622cff76f",
    "name": "Novotel Madrid Center",
    "wikidata": {
      "qid": "Q111388867",
      "label": "Novotel Madrid Center",
      "inception": null,
      "capacity": null,
      "website": null,
      "coord": {
        "lon": -3.67212,
        "lat": 40.42148
      },
      "distance_km": 0.0005811813409920021
    },
    "year_opened": null,
    "candidates": 2
  },
  {
    "booking_hotel_id": "93704",
    "canonical_id": "69922adc-e801-4bca-8c22-a74307fa92cf",
    "name": "Novotel Madrid City Las Ventas",
    "wikidata": {
      "qid": "Q111872122",
      "label": "Novotel Madrid City Las Ventas",
      "inception": null,
      "capacity": null,
      "website": null,
      "coord": {
        "lon": -3.65756,
        "lat": 40.44113
      },
      "distance_km": 0.0005811669379586097
    },
    "year_opened": null,
    "candidates": 2
  },
  {
    "booking_hotel_id": "92895",
    "canonical_id": "982e3779-885c-4fcc-911a-d9630b0ffad5",
    "name": "NYX Hotel Madrid by Leonardo Hotels",
    "wikidata": {
      "qid": "Q111872125",
      "label": "NYX Hotel Madrid by Leonardo Hotels",
      "inception": null,
      "capacity": null,
      "website": null,
      "coord": {
        "lon": -3.69816,
        "lat": 40.4505
      },
      "distance_km": 0.0003374840874104265
    },
    "year_opened": null,
    "candidates": 2
  },
  {
    "booking_hotel_id": "590488",
    "canonical_id": "ea134703-37ff-41dd-b80f-f0ede7aff7fc",
    "name": "Only YOU Boutique Hotel Madrid",
    "wikidata": {
      "qid": "Q111389016",
      "label": "Only YOU Boutique Hotel Madrid",
      "inception": null,
      "capacity": null,
      "website": null,
      "coord": {
        "lon": -3.69574,
        "lat": 40.42227
      },
      "distance_km": 0.000562382089524813
    },
    "year_opened": null,
    "candidates": 2
  },
  {
    "booking_hotel_id": "1674246",
    "canonical_id": "0cf74e8d-56ee-4969-b45c-d02f5ad8f8e8",
    "name": "Only YOU Hotel Atocha",
    "wikidata": {
      "qid": "Q111388628",
      "label": "Only YOU Hotel Atocha",
      "inception": null,
      "capacity": null,
      "website": null,
      "coord": {
        "lon": -3.68832,
        "lat": 40.40717
      },
      "distance_km": 0.00027952352602675124
    },
    "year_opened": null,
    "candidates": 2
  },
  {
    "booking_hotel_id": "91670",
    "canonical_id": "778a45ea-89f4-4201-a6da-1770a10ba6f8",
    "name": "Palacio de los Duques Gran Meliá",
    "wikidata": {
      "qid": "Q111516036",
      "label": "Palacio DE LOS Duques Gran Meliá",
      "inception": null,
      "capacity": null,
      "website": null,
      "coord": {
        "lon": -3.709488362,
        "lat": 40.419827578
      },
      "distance_km": 0.00005604455584531777
    },
    "year_opened": null,
    "candidates": 2
  },
  {
    "booking_hotel_id": "4616969",
    "canonical_id": "f41820ce-b6c0-42c1-8ec3-3ad80f8da632",
    "name": "Pestana Collection Plaza Mayor",
    "wikidata": null,
    "year_opened": null,
    "candidates": 0
  },
  {
    "booking_hotel_id": "7231098",
    "canonical_id": "b0b6ca7a-5baf-4f68-89bd-107d8d8e4587",
    "name": "Pestana CR7 Gran Vía Madrid",
    "wikidata": null,
    "year_opened": null,
    "candidates": 0
  },
  {
    "booking_hotel_id": "91859",
    "canonical_id": "9e91c056-ecda-4833-a355-c1a2f746f8b1",
    "name": "Petit Palace Alcalá",
    "wikidata": {
      "qid": "Q111388751",
      "label": "Petit Palace Alcalá",
      "inception": null,
      "capacity": null,
      "website": "https://www.petitpalace.com/en/petit-palace-alcala/",
      "coord": {
        "lon": -3.69919,
        "lat": 40.4181
      },
      "distance_km": 0.0006987671560078977
    },
    "year_opened": null,
    "candidates": 2
  },
  {
    "booking_hotel_id": "90308",
    "canonical_id": "64a47ef7-9915-4829-b157-f184d3539060",
    "name": "Petit Palace Arturo Soria Alcalá",
    "wikidata": null,
    "year_opened": null,
    "candidates": 0
  },
  {
    "booking_hotel_id": "428878",
    "canonical_id": "3bf09791-e62e-4aea-8b7a-3302cefa8895",
    "name": "Petit Palace Lealtad Plaza",
    "wikidata": {
      "qid": "Q111388743",
      "label": "Petit Palace Lealtad Plaza",
      "inception": null,
      "capacity": null,
      "website": "https://www.petitpalace.com/en/petit-palace-lealtad-plaza/",
      "coord": {
        "lon": -3.691,
        "lat": 40.41672
      },
      "distance_km": 0.00013975448521734576
    },
    "year_opened": null,
    "candidates": 2
  },
  {
    "booking_hotel_id": "92306",
    "canonical_id": "2ed5d47f-5f3e-43bf-ba62-0d1dd4f3dcaf",
    "name": "Petit Palace Plaza del Carmen",
    "wikidata": {
      "qid": "Q111388871",
      "label": "Petit Palace Plaza del Carmen",
      "inception": null,
      "capacity": null,
      "website": "https://www.petitpalace.com/en/petit-palace-plaza-del-carmen/",
      "coord": {
        "lon": -3.70298,
        "lat": 40.41914
      },
      "distance_km": 0.00025396535066391103
    },
    "year_opened": null,
    "candidates": 2
  },
  {
    "booking_hotel_id": "14158",
    "canonical_id": "50cf961b-734a-42ab-9801-af52f701e076",
    "name": "Petit Palace Plaza Mayor",
    "wikidata": {
      "qid": "Q111388749",
      "label": "Petit Palace Plaza Mayor",
      "inception": null,
      "capacity": null,
      "website": "https://www.petitpalace.com/en/petit-palace-plaza-mayor/",
      "coord": {
        "lon": -3.70899,
        "lat": 40.41594
      },
      "distance_km": 0.0006140099849003378
    },
    "year_opened": null,
    "candidates": 2
  },
  {
    "booking_hotel_id": "91564",
    "canonical_id": "92ed7d97-bfbc-4f2a-beb0-6669bcdbbdf5",
    "name": "Petit Palace Posada del Peine",
    "wikidata": {
      "qid": "Q111388746",
      "label": "Petit Palace Posada del Peine",
      "inception": null,
      "capacity": null,
      "website": "https://www.petitpalace.com/en/petit-palace-posada-del-peine/",
      "coord": {
        "lon": -3.70617,
        "lat": 40.41567
      },
      "distance_km": 0.00034415989470792507
    },
    "year_opened": null,
    "candidates": 2
  },
  {
    "booking_hotel_id": "91442",
    "canonical_id": "b1c36ef4-c983-4caf-98a3-0ecf17cec30f",
    "name": "Petit Palace President Castellana",
    "wikidata": {
      "qid": "Q111389153",
      "label": "Petit Palace President Castellana",
      "inception": null,
      "capacity": null,
      "website": "https://www.petitpalace.com/en/petit-palace-president-castellana/",
      "coord": {
        "lon": -3.68841,
        "lat": 40.42922
      },
      "distance_km": 0.00027720638888578116
    },
    "year_opened": null,
    "candidates": 2
  },
  {
    "booking_hotel_id": "38403",
    "canonical_id": "52da201e-c1b0-4344-958b-b35f4c6b9497",
    "name": "Petit Palace Santa Bárbara",
    "wikidata": {
      "qid": "Q111389028",
      "label": "Petit Palace Santa Bárbara",
      "inception": null,
      "capacity": null,
      "website": "https://www.petitpalace.com/en/petit-palace-santa-barbara/",
      "coord": {
        "lon": -3.69637,
        "lat": 40.42643
      },
      "distance_km": 0.00033858377246527674
    },
    "year_opened": null,
    "candidates": 2
  },
  {
    "booking_hotel_id": "313504",
    "canonical_id": "474e43b1-63af-479c-8a48-60da5c770b52",
    "name": "Petit Palace Savoy Alfonso XII",
    "wikidata": {
      "qid": "Q111388744",
      "label": "Petit Palace Savoy Alfonso XII",
      "inception": null,
      "capacity": null,
      "website": "https://www.petitpalace.com/en/petit-palace-savoy-alfonso-xii/",
      "coord": {
        "lon": -3.68934,
        "lat": 40.41726
      },
      "distance_km": 0.0005389351044340272
    },
    "year_opened": null,
    "candidates": 2
  },
  {
    "booking_hotel_id": "189971",
    "canonical_id": "a66329ba-740a-4aaa-89bc-3d3aa4b125cf",
    "name": "Radisson Blu Hotel Madrid Prado",
    "wikidata": null,
    "year_opened": null,
    "candidates": 0
  },
  {
    "booking_hotel_id": "93386",
    "canonical_id": "840dc2e1-361d-4eb1-b170-195ca3f677b9",
    "name": "Radisson RED Madrid",
    "wikidata": null,
    "year_opened": null,
    "candidates": 0
  },
  {
    "booking_hotel_id": "90291",
    "canonical_id": "8e8ddb13-d788-48e1-adfe-a563f8458a8b",
    "name": "Rafaelhoteles Atocha",
    "wikidata": {
      "qid": "Q111388622",
      "label": "Rafaelhoteles Atocha",
      "inception": null,
      "capacity": null,
      "website": null,
      "coord": {
        "lon": -3.68706,
        "lat": 40.40146
      },
      "distance_km": 0.00008467735981409016
    },
    "year_opened": null,
    "candidates": 2
  },
  {
    "booking_hotel_id": "4913077",
    "canonical_id": "3545bb5f-de71-40f9-9c80-c8330609d6f9",
    "name": "Room Mate Collection Alba Madrid",
    "wikidata": null,
    "year_opened": null,
    "candidates": 0
  },
  {
    "booking_hotel_id": "189171",
    "canonical_id": "820c73b0-362e-49b3-be85-6c6cdcadcd82",
    "name": "Rosewood Villa Magna",
    "wikidata": {
      "qid": "Q111389156",
      "label": "Rosewood Villa Magna",
      "inception": null,
      "capacity": null,
      "website": null,
      "coord": {
        "lon": -3.68849,
        "lat": 40.43013
      },
      "distance_km": 0.0004759050097468573
    },
    "year_opened": null,
    "candidates": 2
  },
  {
    "booking_hotel_id": "90032",
    "canonical_id": "4c3bda58-594d-4083-a52c-5a0fab482ea9",
    "name": "Sercotel Gran Hotel Conde Duque",
    "wikidata": {
      "qid": "Q111389168",
      "label": "Sercotel Gran Hotel Conde Duque",
      "inception": null,
      "capacity": null,
      "website": null,
      "coord": {
        "lon": -3.70772,
        "lat": 40.43083
      },
      "distance_km": 0.0002539212163999186
    },
    "year_opened": null,
    "candidates": 2
  },
  {
    "booking_hotel_id": "90381",
    "canonical_id": "c7581282-2e7a-4243-a9c3-89e21ee1689a",
    "name": "Sercotel Madrid Aeropuerto",
    "wikidata": {
      "qid": "Q111872204",
      "label": "Sercotel Madrid Aeropuerto",
      "inception": null,
      "capacity": null,
      "website": null,
      "coord": {
        "lon": -3.58274,
        "lat": 40.45825
      },
      "distance_km": 0.00045275505875392067
    },
    "year_opened": null,
    "candidates": 2
  },
  {
    "booking_hotel_id": "1543865",
    "canonical_id": "86b348a0-6afb-4b5f-bd11-7461bfc5cc14",
    "name": "SmartRental Collection Centric II",
    "wikidata": null,
    "year_opened": null,
    "candidates": 0
  },
  {
    "booking_hotel_id": "4343263",
    "canonical_id": "c7f47b1a-01b6-41dd-83d0-70b719817e02",
    "name": "Smartrental Collection Gran Vía Centric",
    "wikidata": {
      "qid": "Q111871840",
      "label": "SmartRental Collection Gran Via Centric",
      "inception": null,
      "capacity": null,
      "website": null,
      "coord": {
        "lon": -3.70523,
        "lat": 40.42044
      },
      "distance_km": 0.0002772367567804833
    },
    "year_opened": null,
    "candidates": 2
  },
  {
    "booking_hotel_id": "45851",
    "canonical_id": "74d52fd3-5f23-4aa9-bdbb-0b8e3a7195e4",
    "name": "The Principal Madrid Small Luxury Hotels",
    "wikidata": null,
    "year_opened": null,
    "candidates": 0
  },
  {
    "booking_hotel_id": "92520",
    "canonical_id": "45695396-5e18-4001-a670-a5e599de8103",
    "name": "The Westin Madrid Cuzco",
    "wikidata": null,
    "year_opened": null,
    "candidates": 0
  },
  {
    "booking_hotel_id": "8346513",
    "canonical_id": "585030d0-2819-4351-9b62-06d1a9b1a781",
    "name": "Thompson Madrid by Hyatt",
    "wikidata": null,
    "year_opened": null,
    "candidates": 0
  },
  {
    "booking_hotel_id": "91835",
    "canonical_id": "33f45d9d-fb98-4fe5-b68e-5b75bec9805f",
    "name": "TÓTEM Madrid",
    "wikidata": null,
    "year_opened": null,
    "candidates": 0
  },
  {
    "booking_hotel_id": "1066415",
    "canonical_id": "a879af8f-ad84-4446-b56e-173d0b7b15c0",
    "name": "URSO Hotel & Spa",
    "wikidata": {
      "qid": "Q111389030",
      "label": "Urso Hotel & Spa, a Small Luxury Hotel of the World",
      "inception": null,
      "capacity": null,
      "website": null,
      "coord": {
        "lon": -3.6982398,
        "lat": 40.426865
      },
      "distance_km": 0.00011247624356020643
    },
    "year_opened": null,
    "candidates": 2
  },
  {
    "booking_hotel_id": "93683",
    "canonical_id": "a9a68cc9-406c-4893-8103-18c893bfeb97",
    "name": "Vincci Capitol",
    "wikidata": {
      "qid": "Q111388883",
      "label": "Vincci Capitol",
      "inception": null,
      "capacity": null,
      "website": "https://en.vinccicapitol.com/",
      "coord": {
        "lon": -3.706487,
        "lat": 40.42037
      },
      "distance_km": 0.00022238985272763707
    },
    "year_opened": null,
    "candidates": 2
  },
  {
    "booking_hotel_id": "91173",
    "canonical_id": "4099bcef-b2df-4935-a0a7-1356daa4ea02",
    "name": "Vincci Centrum",
    "wikidata": {
      "qid": "Q111516031",
      "label": "Vincci Centrum Hotel Madrid",
      "inception": null,
      "capacity": null,
      "website": "https://en.vinccicentrum.com/",
      "coord": {
        "lon": -3.698589205,
        "lat": 40.417559895
      },
      "distance_km": 0.00002091655777517791
    },
    "year_opened": null,
    "candidates": 2
  },
  {
    "booking_hotel_id": "91861",
    "canonical_id": "269303e1-8b45-4d87-8b6f-5aafb133a198",
    "name": "Vincci Soho",
    "wikidata": null,
    "year_opened": null,
    "candidates": 0
  },
  {
    "booking_hotel_id": "90479",
    "canonical_id": "a1b1cee6-ec8f-4946-a6e0-9a7f7fc9cb6a",
    "name": "Vincci Soma",
    "wikidata": null,
    "year_opened": null,
    "candidates": 0
  },
  {
    "booking_hotel_id": "1676516",
    "canonical_id": "b6e4cb35-7c9e-450a-ad38-4243ec2966dc",
    "name": "Vincci The Mint",
    "wikidata": null,
    "year_opened": null,
    "candidates": 0
  },
  {
    "booking_hotel_id": "94672",
    "canonical_id": "e14ba7b1-0162-4514-8fc9-a221728eca99",
    "name": "Vincci Vía 66",
    "wikidata": null,
    "year_opened": null,
    "candidates": 0
  },
  {
    "booking_hotel_id": "631351",
    "canonical_id": "7b1e0026-5a85-4f70-85a9-562e12b318a8",
    "name": "voco Madrid Las Tablas by IHG",
    "wikidata": null,
    "year_opened": null,
    "candidates": 0
  },
  {
    "booking_hotel_id": "93358",
    "canonical_id": "19e31ed2-8ef5-47ca-bb08-f42efae58ece",
    "name": "voco Madrid Retiro by IHG",
    "wikidata": null,
    "year_opened": null,
    "candidates": 0
  }
]